mkstm32/__init__.py
mkstm32/cli.py
mkstm32/config.py
mkstm32/helpers.py
mkstm32/project.py
mkstm32/stlink.py
mkstm32/version.py
mkstm32-1.6.13.data/scripts/mkstm32
mkstm32-1.6.13.dist-info/METADATA
mkstm32-1.6.13.dist-info/WHEEL
mkstm32-1.6.13.dist-info/top_level.txt
mkstm32-1.6.13.dist-info/RECORD
