Metadata-Version: 2.1
Name: mkstm32
Version: 1.6.13
Summary: Upload, debug and compile STM32CubeMX Makefile projects
Home-page: https://github.com/adzierzanowski/mkstm32
Author: Aleksander Dzierżanowski
Author-email: a.dzierzanowski1@gmail.com
License: MIT
Platform: UNKNOWN
Requires-Dist: pyserial
